ipipeline/__init__.py
ipipeline/__main__.py
ipipeline/exceptions.py
ipipeline/cli/__init__.py
ipipeline/cli/actions.py
ipipeline/cli/arguments.py
ipipeline/cli/commands.py
ipipeline/cli/execution.py
ipipeline/cli/parsing.py
ipipeline/control/__init__.py
ipipeline/control/building.py
ipipeline/control/executors.py
ipipeline/control/sorting.py
ipipeline/structure/__init__.py
ipipeline/structure/catalog.py
ipipeline/structure/info.py
ipipeline/structure/link.py
ipipeline/structure/node.py
ipipeline/structure/pipeline.py
ipipeline/utils/__init__.py
ipipeline/utils/checking.py
ipipeline/utils/instance.py
ipipeline/utils/system.py
ipipeline-0.17.0.dist-info/METADATA
ipipeline-0.17.0.dist-info/WHEEL
ipipeline-0.17.0.dist-info/licenses/LICENSE.md
ipipeline-0.17.0.dist-info/RECORD
