Metadata-Version: 2.1
Name: ipipeline
Version: 0.17.0
Summary: A micro framework to build and execute pipelines from different domains.
Project-URL: GitHub, https://github.com/novaenext/ipipeline
Author: novaenext
Keywords: data,etl,pipeline
Classifier: License :: OSI Approved :: BSD License
Classifier: Operating System :: OS Independent
Classifier: Programming Language :: Python :: 3
Requires-Python: >=3.6
